scskutils/__init__.py
scskutils/decorators.py
scskutils/scraper.py
scskutils/scskutils.py
scskutils/translator.py
scskutils/visuals.py
SCSKutils-0.1.1.dist-info/METADATA
SCSKutils-0.1.1.dist-info/WHEEL
SCSKutils-0.1.1.dist-info/top_level.txt
SCSKutils-0.1.1.dist-info/RECORD
