Metadata-Version: 2.1
Name: SCSKutils
Version: 0.1.1
Summary: SCSK DX data team utils package.
Home-page: UNKNOWN
Author: emelas (Elias Melas)
Author-email: <elias.melas@scskeu.com>
License: UNKNOWN
Platform: UNKNOWN
Requires-Dist: sqlalchemy
Requires-Dist: pyodbc
Requires-Dist: deep-translator
